Metadata-Version: 2.1
Name: squareapi-py
Version: 0.0.4
Summary: Uma biblioteca que ultilizar a api da squarecloud
Home-page: UNKNOWN
Author: Astro
Author-email: ericksantosyb@gmail.com
License: MIT License
Keywords: square_lib
Platform: UNKNOWN
License-File: LICENCE
